CHANGELOG.txt
LICENSE.txt
MANIFEST.in
README.txt
setup.py
CVPRW2019_Face_Artifacts/__init__.py
CVPRW2019_Face_Artifacts/deleteme.py
CVPRW2019_Face_Artifacts/demo.py
CVPRW2019_Face_Artifacts/resolution_network.py
CVPRW2019_Face_Artifacts/setup.py
CVPRW2019_Face_Artifacts/solver.py
CVPRW2019_Face_Artifacts/py_utils/__init__.py
CVPRW2019_Face_Artifacts/py_utils/plot.py
CVPRW2019_Face_Artifacts/py_utils/vis.py
CVPRW2019_Face_Artifacts/py_utils/face_utils/__init__.py
CVPRW2019_Face_Artifacts/py_utils/face_utils/dlib_utils.py
CVPRW2019_Face_Artifacts/py_utils/face_utils/lib.py
CVPRW2019_Face_Artifacts/py_utils/face_utils/umeyama.py
CVPRW2019_Face_Artifacts/py_utils/img_utils/__init__.py
CVPRW2019_Face_Artifacts/py_utils/img_utils/proc_img.py
CVPRW2019_Face_Artifacts/py_utils/plot_utils/__init__.py
CVPRW2019_Face_Artifacts/py_utils/plot_utils/plot.py
CVPRW2019_Face_Artifacts/py_utils/vid_utils/__init__.py
CVPRW2019_Face_Artifacts/py_utils/vid_utils/proc_aud.py
CVPRW2019_Face_Artifacts/py_utils/vid_utils/proc_vid.py
CVPRW2019_Face_Artifacts/tf_utils/__init__.py
CVPRW2019_Face_Artifacts/tf_utils/utils.py
facewarpingmodulev1.egg-info/PKG-INFO
facewarpingmodulev1.egg-info/SOURCES.txt
facewarpingmodulev1.egg-info/dependency_links.txt
facewarpingmodulev1.egg-info/requires.txt
facewarpingmodulev1.egg-info/top_level.txt